googleapiwrapper/__init__.py
googleapiwrapper/common.py
googleapiwrapper/gmail_api.py
googleapiwrapper/gmail_api_extensions.py
googleapiwrapper/gmail_cache.py
googleapiwrapper/gmail_common.py
googleapiwrapper/gmail_domain.py
googleapiwrapper/google_auth.py
googleapiwrapper/google_calendar.py
googleapiwrapper/google_drive.py
googleapiwrapper/google_sheet.py
googleapiwrapper/utils.py
google_api_wrapper2-1.0.19.dist-info/LICENSE
google_api_wrapper2-1.0.19.dist-info/METADATA
google_api_wrapper2-1.0.19.dist-info/WHEEL
google_api_wrapper2-1.0.19.dist-info/RECORD
