Metadata-Version: 2.1
Name: google-api-wrapper2
Version: 1.0.19
Summary: 
Author: Szilard Nemeth
Author-email: szilard.nemeth88@gmail.com
Requires-Python: >=3.8,<4.0
Classifier: Programming Language :: Python :: 3
Classifier: Programming Language :: Python :: 3.8
Classifier: Programming Language :: Python :: 3.9
Classifier: Programming Language :: Python :: 3.10
Classifier: Programming Language :: Python :: 3.11
Classifier: Programming Language :: Python :: 3.12
Requires-Dist: google-api-python-client (==2.31.0)
Requires-Dist: google-auth-httplib2 (==0.1.0)
Requires-Dist: google-auth-oauthlib (==0.4.6)
Requires-Dist: gspread (>=5.1.1)
Requires-Dist: oauth2client (>=4.1.3,<5.0.0)
Requires-Dist: python-common-lib (==1.0.18)
Requires-Dist: pyyaml (==6.0.1)
